ksx1026/__init__.py
ksx1026/constants.py
ksx1026/normalization.py
ksx1026/sorting.py
ksx1026/uchar.py
ksx1026-0.0.1.dist-info/DESCRIPTION.rst
ksx1026-0.0.1.dist-info/METADATA
ksx1026-0.0.1.dist-info/RECORD
ksx1026-0.0.1.dist-info/WHEEL
ksx1026-0.0.1.dist-info/metadata.json
ksx1026-0.0.1.dist-info/top_level.txt
tests/__init__.py
tests/test_enclosed.py
tests/test_moden_jamo.py
tests/test_modern_jamo.py
tests/test_modern_syllable.py
tests/test_syllable.py
