Metadata-Version: 2.0
Name: ksx1026
Version: 0.0.1
Summary: Python Implementation of KS X 1026 
Home-page: https://github.com/Pusnow/KS-X-1026-Python
Author: Wonsup Yoon
Author-email: pusnow@yonsei.ac.kr
License: MIT
Keywords: hangul unicode
Platform: UNKNOWN
